{"nodes": [{"id": "ui_src_hooks_infra_usepollingquery_ts", "label": "usePollingQuery.ts", "file_type": "code", "source_file": "ui\\src\\hooks\\infra\\usePollingQuery.ts", "source_location": "L1"}, {"id": "usepollingquery_usepollingquery", "label": "usePollingQuery()", "file_type": "code", "source_file": "ui\\src\\hooks\\infra\\usePollingQuery.ts", "source_location": "L14"}], "edges": [{"source": "ui_src_hooks_infra_usepollingquery_ts", "target": "react", "relation": "imports_from", "confidence": "EXTRACTED", "source_file": "ui\\src\\hooks\\infra\\usePollingQuery.ts", "source_location": "L1", "weight": 1.0}, {"source": "ui_src_hooks_infra_usepollingquery_ts", "target": "ui_src_hooks_infra_useintervalwhen", "relation": "imports_from", "confidence": "EXTRACTED", "source_file": "ui\\src\\hooks\\infra\\usePollingQuery.ts", "source_location": "L3", "weight": 1.0}, {"source": "ui_src_hooks_infra_usepollingquery_ts", "target": "usepollingquery_usepollingquery", "relation": "contains", "confidence": "EXTRACTED", "source_file": "ui\\src\\hooks\\infra\\usePollingQuery.ts", "source_location": "L14", "weight": 1.0}], "raw_calls": [{"caller_nid": "usepollingquery_usepollingquery", "callee": "useState", "source_file": "ui\\src\\hooks\\infra\\usePollingQuery.ts", "source_location": "L15"}, {"caller_nid": "usepollingquery_usepollingquery", "callee": "useRef", "source_file": "ui\\src\\hooks\\infra\\usePollingQuery.ts", "source_location": "L16"}, {"caller_nid": "usepollingquery_usepollingquery", "callee": "useRef", "source_file": "ui\\src\\hooks\\infra\\usePollingQuery.ts", "source_location": "L17"}, {"caller_nid": "usepollingquery_usepollingquery", "callee": "useRef", "source_file": "ui\\src\\hooks\\infra\\usePollingQuery.ts", "source_location": "L18"}, {"caller_nid": "usepollingquery_usepollingquery", "callee": "useRef", "source_file": "ui\\src\\hooks\\infra\\usePollingQuery.ts", "source_location": "L19"}, {"caller_nid": "usepollingquery_usepollingquery", "callee": "useCallback", "source_file": "ui\\src\\hooks\\infra\\usePollingQuery.ts", "source_location": "L24"}, {"caller_nid": "usepollingquery_usepollingquery", "callee": "useEffect", "source_file": "ui\\src\\hooks\\infra\\usePollingQuery.ts", "source_location": "L36"}, {"caller_nid": "usepollingquery_usepollingquery", "callee": "useIntervalWhen", "source_file": "ui\\src\\hooks\\infra\\usePollingQuery.ts", "source_location": "L44"}, {"caller_nid": "usepollingquery_usepollingquery", "callee": "useEffect", "source_file": "ui\\src\\hooks\\infra\\usePollingQuery.ts", "source_location": "L46"}]}